{
"skeleton": {
	"hash": "9nrDnbVBWv5S0IkIKFvevlkHaoc",
	"spine": "3.8.99",
	"x": -105.41,
	"y": -2.82,
	"width": 227.82,
	"height": 352.4,
	"images": "",
	"audio": ""
},
"bones": [
	{ "name": "root" },
	{ "name": "Body", "parent": "root", "length": 36.78, "rotation": 90, "x": 2.05, "y": 120.58 },
	{ "name": "Chest", "parent": "Body", "length": 25.39, "rotation": 1.17, "x": 36.78, "y": -0.52 },
	{ "name": "Neck", "parent": "Chest", "length": 16.58, "rotation": 0.62, "x": 26.96, "y": 1 },
	{ "name": "Head", "parent": "Neck", "length": 63.3, "rotation": -5.07, "x": 16.58 },
	{ "name": "HandL_1", "parent": "Chest", "length": 39.9, "rotation": 87.34, "x": 23.97, "y": 6.6 },
	{ "name": "HandL_2", "parent": "HandL_1", "length": 52.34, "rotation": -0.21, "x": 39.9 },
	{ "name": "HandR_1", "parent": "Chest", "length": 47.14, "rotation": -91.17, "x": 23.78, "y": -2.56 },
	{ "name": "HandR_2", "parent": "HandR_1", "length": 56.46, "x": 47.14 },
	{ "name": "LegL_1", "parent": "Body", "length": 45.09, "rotation": 178.03, "y": 9.32 },
	{ "name": "LegL_2", "parent": "LegL_1", "length": 78.16, "rotation": -11.05, "x": 45.11, "y": -0.52 },
	{ "name": "LegR_1", "parent": "Body", "length": 47.87, "rotation": -166.87, "x": 1.55, "y": -8.81 },
	{ "name": "LegR_2", "parent": "LegR_1", "length": 76.23, "rotation": -10.41, "x": 47.37, "y": 0.12 },
	{ "name": "sword", "parent": "HandR_2", "x": 24.62, "y": -13.42 },
	{ "name": "LegL", "parent": "root", "x": -30.13, "y": -2.14, "color": "ff3f00ff" },
	{ "name": "LegR", "parent": "root", "x": 25.58, "y": -1.49, "color": "ff3f00ff" },
	{ "name": "EffectSword", "parent": "sword", "x": -21.67, "y": 35.93 },
	{ "name": "Weapon_R", "parent": "HandL_2", "x": 40.82 },
	{ "name": "EffectSword2", "parent": "HandL_2", "rotation": -178.3, "x": 58.52, "y": -35.29 }
],
"slots": [
	{ "name": "Weapon_L", "bone": "sword", "attachment": "sword2" },
	{ "name": "Weapon_R", "bone": "Weapon_R", "attachment": "Weapon_R" },
	{ "name": "hand", "bone": "HandL_1", "attachment": "hand2" },
	{ "name": "hand2", "bone": "HandR_1", "attachment": "hand2" },
	{ "name": "MC", "bone": "Body", "attachment": "MC2" },
	{ "name": "EffectSword", "bone": "EffectSword" },
	{ "name": "EffectSword2", "bone": "EffectSword2" }
],
"ik": [
	{
		"name": "LegL",
		"bones": [ "LegL_1", "LegL_2" ],
		"target": "LegL",
		"bendPositive": false
	},
	{
		"name": "LegR",
		"order": 1,
		"bones": [ "LegR_1", "LegR_2" ],
		"target": "LegR",
		"bendPositive": false
	}
],
"skins": [
	{
		"name": "default",
		"attachments": {
			"EffectSword": {
				"Attack1_1": { "x": -164.42, "y": 0.5, "width": 374, "height": 301 },
				"Attack1_2": { "x": -163.37, "y": 0.5, "width": 374, "height": 301 },
				"Attack1_3": { "x": -164.42, "y": 0.5, "width": 374, "height": 301 },
				"Attack1_4": { "x": -163.37, "y": 0.5, "width": 374, "height": 301 },
				"Attack1_5": { "x": -163.37, "y": 0.5, "width": 374, "height": 301 }
			},
			"EffectSword2": {
				"Attack1_1": { "x": -164.42, "y": 0.5, "width": 374, "height": 301 },
				"Attack1_2": { "x": -163.37, "y": 0.5, "width": 374, "height": 301 },
				"Attack1_3": { "x": -164.42, "y": 0.5, "width": 374, "height": 301 },
				"Attack1_4": { "x": -163.37, "y": 0.5, "width": 374, "height": 301 },
				"Attack1_5": { "x": -163.37, "y": 0.5, "width": 374, "height": 301 }
			}
		}
	},
	{
		"name": "Sword_2",
		"attachments": {
			"MC": {
				"MC2": {
					"name": "MC-2",
					"type": "mesh",
					"uvs": [ 0.27169, 0.10758, 0.24061, 0.18634, 0.28334, 0.23155, 0.41153, 0.28114, 0.39599, 0.31177, 0.23284, 0.26801, 0.06969, 0.22426, 0.15126, 0.28989, 0.23284, 0.35552, 0.22119, 0.41678, 0.30276, 0.42845, 0.36966, 0.52177, 0.42753, 0.57996, 0.36055, 0.61488, 0.43125, 0.69033, 0.34085, 0.75149, 0.25044, 0.81266, 0.3007, 0.90633, 0.35095, 1, 0.5018, 1, 0.53822, 0.9268, 0.56943, 0.82133, 0.60064, 0.71586, 0.60064, 0.67876, 0.64915, 0.62903, 0.6318, 0.59644, 0.67292, 0.60708, 0.66208, 0.65052, 0.71269, 0.70142, 0.65822, 0.85014, 0.7439, 0.92016, 0.87945, 1, 1, 1, 0.96354, 0.90506, 0.92707, 0.81013, 0.88311, 0.70697, 0.90143, 0.5818, 0.84648, 0.55979, 0.86068, 0.4169, 0.94045, 0.38959, 0.91288, 0.35521, 0.9808, 0.23053, 0.8268, 0.29557, 0.7918, 0.28309, 0.8373, 0.27455, 0.9213, 0.23972, 0.98605, 0.19833, 1, 0.13591, 0.93031, 0.05282, 0.7736, 0.02137, 0.57906, 0.01833, 0.46178, 0.01375, 0.34451, 0.00916, 0.22723, 0.00458, 0.10996, 0, 0.28829, 0.03533, 0.14414, 0.02002, 0, 0.00472, 0, 0.01849, 0.18229, 0.07819, 0.66876, 0.16922, 0.58192, 0.49513, 0.45515, 0.78646, 0.63535, 0.35891, 0.46912, 0.07885, 0.58109, 0.2808, 0.84173, 0.91609, 0.39885, 0.88167, 0.41826, 0.19063, 0.54871, 0.43323, 0.73639, 0.07949, 0.69402, 0.50021, 0.79523, 0.7672, 0.42312, 0.3776, 0.76653, 0.64955, 0.8642, 0.12716, 0.52139, 0.14158, 0.56528, 0.22431, 0.82152, 0.86144, 0.66443, 0.44095 ],
					"triangles": [ 63, 4, 65, 65, 4, 3, 63, 43, 42, 63, 65, 43, 8, 5, 4, 60, 44, 43, 3, 77, 65, 3, 68, 77, 3, 2, 68, 43, 65, 77, 45, 44, 60, 60, 43, 77, 2, 1, 68, 46, 45, 60, 46, 60, 75, 68, 76, 77, 77, 76, 60, 46, 75, 47, 1, 0, 68, 76, 68, 0, 76, 0, 64, 64, 0, 55, 55, 51, 64, 55, 52, 51, 60, 70, 75, 60, 76, 70, 76, 64, 70, 75, 48, 47, 75, 70, 48, 0, 59, 55, 64, 50, 70, 70, 49, 48, 70, 50, 49, 64, 51, 50, 58, 56, 59, 59, 56, 55, 55, 54, 53, 55, 53, 52, 56, 58, 57, 25, 61, 71, 37, 71, 38, 11, 69, 61, 11, 10, 69, 61, 79, 71, 71, 79, 38, 61, 69, 79, 38, 79, 63, 10, 73, 69, 79, 69, 63, 69, 73, 63, 73, 10, 8, 38, 40, 39, 38, 63, 40, 10, 9, 8, 8, 4, 73, 63, 73, 4, 63, 42, 40, 40, 42, 41, 14, 23, 22, 14, 13, 23, 23, 13, 24, 24, 12, 25, 12, 24, 13, 12, 61, 25, 12, 11, 61, 72, 28, 35, 28, 74, 35, 35, 74, 36, 28, 27, 74, 74, 27, 26, 36, 26, 37, 36, 74, 26, 26, 25, 37, 25, 71, 37, 19, 18, 20, 20, 17, 67, 20, 18, 17, 21, 20, 67, 17, 16, 67, 67, 62, 21, 67, 16, 62, 21, 62, 22, 16, 15, 62, 15, 14, 62, 62, 14, 22, 31, 33, 32, 30, 66, 31, 31, 66, 33, 30, 78, 66, 30, 29, 78, 66, 78, 33, 78, 34, 33, 34, 78, 72, 28, 72, 29, 78, 29, 72, 72, 35, 34, 7, 5, 8, 7, 6, 5 ],
					"vertices": [ 2, 4, 41.16, 42.17, 0.99683, 3, 61.31, 38.36, 0.00317, 2, 4, 19.2, 44.14, 0.92977, 3, 39.61, 42.27, 0.07023, 3, 4, 6.95, 38.99, 0.83658, 3, 26.95, 38.22, 0.16333, 9, -82.84, -45.67, 8.0E-5, 5, 4, -6, 24.89, 0.39998, 3, 12.81, 25.33, 0.59232, 2, 39.49, 26.47, 2.0E-4, 1, 75.72, 26.75, 2.9E-4, 9, -71.6, -30.18, 0.00721, 5, 4, -14.56, 26.02, 0.08993, 3, 4.38, 27.21, 0.84616, 2, 31.04, 28.26, 0.02363, 1, 67.24, 28.37, 0.01022, 9, -62.97, -30.31, 0.03006, 5, 4, -3.44, 43.65, 4.2E-4, 3, 17.02, 43.79, 0.96652, 2, 43.51, 44.97, 4.2E-4, 1, 79.36, 45.33, 8.0E-4, 9, -71.99, -49.11, 0.03185, 5, 4, 7.69, 61.29, 0, 3, 29.67, 60.37, 0.97638, 2, 55.97, 61.69, 1.0E-5, 1, 91.48, 62.3, 1.0E-5, 9, -81.02, -67.91, 0.0236, 4, 3, 11.23, 52.46, 0.96613, 2, 37.62, 53.58, 8.6E-4, 1, 73.3, 53.82, 0.00116, 9, -64.57, -56.43, 0.03185, 5, 4, -27.64, 42.27, 5.8E-4, 3, -7.21, 44.54, 0.8281, 2, 19.27, 45.47, 0.05371, 1, 55.12, 45.33, 0.04681, 9, -48.11, -44.94, 0.07081, 4, 3, -24.13, 46.29, 0.63225, 2, 2.33, 47.03, 0.10591, 1, 38.15, 46.55, 0.12689, 9, -31.19, -43.22, 0.13495, 4, 3, -27.62, 37.91, 0.51224, 2, -1.07, 38.61, 0.12239, 1, 34.92, 38.06, 0.18263, 9, -29.46, -34.31, 0.18274, 4, 3, -53.68, 31.76, 0.08345, 2, -27.06, 32.18, 0.0235, 1, 9.07, 31.1, 0.18172, 9, -5.19, -23.01, 0.71132, 4, 3, -69.98, 26.25, 0.00607, 2, -43.3, 26.49, 2.4E-4, 1, -7.05, 25.09, 0.00221, 9, 9.65, -14.32, 0.99148, 1, 9, 20.38, -19.52, 1, 2, 9, 39.7, -8.68, 0.85454, 10, -5.31, -8.23, 0.14546, 1, 10, 13.06, -14.37, 1, 1, 10, 31.44, -20.51, 1, 1, 10, 55.99, -10.62, 1, 1, 10, 80.55, -0.73, 1, 1, 10, 77.67, 14.69, 1, 1, 10, 57.04, 14.7, 1, 1, 10, 27.73, 12.55, 1, 2, 9, 43.65, 9.89, 0.56971, 10, -1.58, 10.39, 0.43029, 3, 1, -34.42, 7.08, 1.7E-4, 9, 33.52, 8.12, 0.99119, 10, -11.69, 8.51, 0.00865, 3, 1, -20.64, 2.04, 0.03776, 9, 19.08, 10.72, 0.94691, 11, 20.79, -13.34, 0.01533, 3, 1, -11.62, 3.84, 0.19792, 9, 10.5, 7.4, 0.62388, 11, 11.62, -14.09, 0.1782, 3, 1, -14.56, -0.44, 0.15518, 9, 12.67, 12.12, 0.16091, 11, 15.04, -10.18, 0.68391, 3, 1, -26.6, 0.69, 0.01809, 9, 24.72, 13.07, 0.00816, 11, 26.86, -12.69, 0.97374, 2, 11, 41.47, -9.1, 0.89449, 12, -5.92, -9.2, 0.10551, 1, 12, 34.32, -19.7, 1, 1, 12, 54.63, -13.15, 1, 1, 12, 78.26, -1.76, 1, 1, 12, 79.74, 10.69, 1, 1, 12, 53.18, 10.03, 1, 1, 12, 26.62, 9.38, 1, 2, 11, 45.05, 8.33, 0.7036, 12, -2.29, 8.22, 0.2964, 1, 11, 10.84, 14.23, 1, 1, 11, 4.12, 9.26, 1, 3, 2, 0.94, -19.47, 0.65237, 1, 38.12, -19.96, 0.31982, 11, -35.03, 15.32, 0.02781, 4, 3, -18.94, -28.72, 0.01072, 2, 8.34, -27.92, 0.87132, 1, 45.68, -28.26, 0.11278, 11, -41.58, 24.43, 0.00518, 4, 3, -9.33, -26.15, 0.06003, 2, 17.92, -25.24, 0.90307, 1, 55.21, -25.39, 0.03633, 11, -51.37, 22.69, 5.6E-4, 4, 4, 11.39, -33.41, 2.0E-5, 3, 24.97, -34.29, 0.2215, 2, 52.3, -33.01, 0.77848, 1, 89.74, -32.45, 0, 3, 4, -7.52, -18.45, 0.08201, 3, 7.46, -17.72, 0.27506, 2, 34.62, -16.63, 0.64293, 3, 4, -4.28, -14.62, 0.302, 3, 11.03, -14.19, 0.38845, 2, 38.15, -13.06, 0.30954, 3, 4, -1.64, -19.21, 0.6138, 3, 13.25, -18.99, 0.25385, 2, 40.42, -17.84, 0.13236, 3, 4, 8.49, -27.38, 0.92245, 3, 22.62, -28.02, 0.0625, 2, 49.88, -26.77, 0.01505, 2, 4, 20.32, -33.44, 0.99425, 3, 33.87, -35.11, 0.00575, 1, 4, 37.67, -33.9, 1, 1, 4, 60.23, -25.35, 1, 1, 4, 67.99, -8.58, 1, 1, 4, 67.67, 11.67, 1, 1, 4, 68.24, 23.92, 1, 1, 4, 68.81, 36.17, 1, 1, 4, 69.38, 48.42, 1, 1, 4, 69.95, 60.67, 1, 1, 4, 61.24, 41.59, 1, 1, 4, 64.62, 56.8, 1, 1, 4, 67.99, 72.01, 1, 1, 4, 64.18, 71.79, 1, 1, 4, 48.76, 51.92, 1, 1, 4, 26.48, -0.04, 1, 4, 3, -46.99, 9.47, 0.02687, 2, -20.13, 9.96, 0.01012, 1, 16.45, 9.03, 0.71863, 9, -16.26, -2.54, 0.24437, 1, 10, 20.41, -0.91, 1, 3, 3, -9.45, 2.73, 0.17375, 2, 17.48, 3.63, 0.8221, 9, -54.38, -3.54, 0.00415, 1, 4, 50.28, 22.12, 1, 3, 4, -4.9, 7.29, 0.23368, 3, 12.35, 7.7, 0.76471, 9, -74.73, -12.82, 0.00161, 1, 12, 54.72, -2.91, 1, 1, 10, 47.41, -1.83, 1, 2, 4, 19.07, 25.63, 0.92705, 3, 37.84, 23.84, 0.07295, 4, 3, -29.75, 12.38, 0.15635, 2, -2.92, 13.06, 0.25388, 1, 33.59, 12.48, 0.48305, 9, -32.55, -8.88, 0.10672, 1, 4, 51.7, -5.64, 1, 2, 1, 15.04, -2.63, 0.92661, 11, -14.11, -4.57, 0.07339, 1, 12, 13.19, -2.83, 1, 5, 4, -32.61, 22.16, 0.00245, 3, -13.94, 24.96, 0.64323, 2, 12.76, 25.81, 0.18172, 1, 49, 25.54, 0.09296, 9, -45.49, -24.4, 0.07964, 3, 1, -26.33, -10.17, 0.00183, 9, 22.59, 23.73, 5.8E-4, 11, 27.85, -1.87, 0.99759, 1, 4, 39.28, -19.66, 1, 2, 4, 33.25, 15.7, 0.99926, 3, 51.09, 12.7, 7.4E-4, 3, 4, 10.63, 9.83, 0.92875, 3, 28.04, 8.85, 0.0712, 9, -89.86, -17.13, 5.0E-5, 1, 12, 39.44, -3.21, 1, 3, 3, -32.26, 0.42, 0.00228, 1, 31.46, 0.45, 0.99548, 9, -32.51, 3.34, 0.00224 ],
					"hull": 60,
					"edges": [ 0, 2, 2, 4, 4, 6, 6, 8, 8, 10, 10, 12, 12, 14, 14, 16, 16, 18, 18, 20, 20, 22, 22, 24, 24, 26, 26, 28, 28, 30, 30, 32, 32, 34, 34, 36, 36, 38, 38, 40, 40, 42, 42, 44, 44, 46, 46, 48, 48, 50, 50, 52, 52, 54, 54, 56, 56, 58, 58, 60, 60, 62, 62, 64, 64, 66, 66, 68, 68, 70, 70, 72, 72, 74, 74, 76, 76, 78, 78, 80, 80, 82, 82, 84, 84, 86, 86, 88, 88, 90, 90, 92, 92, 94, 94, 96, 96, 98, 98, 100, 100, 102, 102, 104, 104, 106, 106, 108, 108, 110, 110, 112, 112, 114, 114, 116, 116, 118, 118, 0 ],
					"width": 104,
					"height": 277
				}
			},
			"Weapon_L": {
				"sword2": { "name": "sword", "x": 2.51, "y": 73.32, "width": 87, "height": 217 }
			},
			"hand": {
				"hand2": {
					"name": "hand",
					"type": "mesh",
					"uvs": [ 0.20547, 1, 0.42389, 0.80479, 0.5149, 0.67602, 0.60591, 0.54725, 0.83343, 0.54725, 1, 0.58541, 1, 0.36602, 1, 0.14664, 0.83116, 0.09895, 0.60136, 0.15618, 0.37384, 0, 0.13039, 0, 0.06519, 0.18778, 0, 0.37556, 0, 0.5711, 0, 0.76664, 0.20092, 1, 0.19072, 0.56349, 0.5012, 0.37697, 0.32522, 0.50072, 0.25524, 0.26487, 0.71803, 0.33751, 0.28021, 0.62758, 0.07632, 0.57801 ],
					"triangles": [ 20, 11, 10, 18, 10, 9, 19, 20, 10, 19, 10, 18, 17, 11, 20, 12, 11, 17, 23, 14, 13, 12, 23, 13, 17, 23, 12, 22, 20, 19, 17, 20, 22, 2, 18, 3, 15, 14, 23, 1, 19, 18, 1, 18, 2, 0, 16, 17, 23, 17, 16, 15, 23, 16, 22, 0, 17, 1, 0, 22, 1, 22, 19, 21, 9, 8, 8, 7, 6, 3, 9, 21, 18, 9, 3, 4, 8, 6, 21, 8, 4, 3, 21, 4, 4, 6, 5 ],
					"vertices": [ 1, 6, 38.34, 15.21, 1, 1, 6, 14.55, 10.05, 1, 2, 5, 44.57, 6.65, 0.00948, 6, 4.65, 6.66, 0.99052, 2, 5, 34.65, 3.3, 0.99125, 6, -5.26, 3.28, 0.00875, 1, 5, 9.85, 3.3, 1, 1, 5, -8.3, 4.29, 1, 1, 5, -8.3, -1.41, 1, 1, 5, -8.3, -7.12, 1, 1, 5, 10.1, -8.36, 1, 2, 5, 35.15, -6.87, 0.8726, 6, -4.73, -6.89, 0.1274, 1, 6, 20.09, -10.86, 1, 1, 6, 46.62, -10.76, 1, 1, 6, 53.71, -5.85, 1, 1, 6, 60.8, -0.94, 1, 1, 6, 60.78, 4.14, 1, 1, 6, 60.76, 9.23, 1, 1, 6, 38.84, 15.21, 1, 1, 6, 39.99, 3.87, 1, 2, 5, 46.06, -1.13, 0.00107, 6, 6.17, -1.11, 0.99893, 1, 6, 25.34, 2.18, 1, 1, 6, 32.99, -3.92, 1, 1, 5, 22.43, -2.15, 1, 1, 6, 30.23, 5.5, 1, 1, 6, 52.46, 4.29, 1 ],
					"hull": 17,
					"edges": [ 0, 2, 2, 4, 4, 6, 6, 8, 8, 10, 10, 12, 12, 14, 14, 16, 16, 18, 18, 20, 20, 22, 22, 24, 24, 26, 26, 28, 28, 30, 30, 32, 32, 0 ],
					"width": 109,
					"height": 26
				}
			},
			"hand2": {
				"hand2": {
					"name": "hand",
					"type": "mesh",
					"uvs": [ 0.59166, 0.53641, 0.49715, 0.66071, 0.40263, 0.78502, 0.29978, 0.89251, 0.19693, 1, 0.07276, 0.85494, 0, 0.66848, 0, 0.53252, 0, 0.39656, 0.06696, 0.19828, 0.13392, 0, 0.36742, 0.07802, 0.58239, 0.2101, 0.8006, 0.20505, 1, 0.17898, 1, 0.38759, 1, 0.59621, 0.79231, 0.50928, 0.23472, 0.54212, 0.48575, 0.40203, 0.12244, 0.53498, 0.21528, 0.28782, 0.34111, 0.4194, 0.69201, 0.36475, 0.91815, 0.37536, 0.2585, 0.2648 ],
					"triangles": [ 25, 10, 11, 21, 10, 25, 19, 11, 12, 22, 25, 11, 22, 11, 19, 20, 7, 8, 20, 9, 10, 20, 10, 21, 20, 8, 9, 18, 21, 25, 18, 25, 22, 20, 21, 18, 1, 19, 0, 5, 6, 7, 2, 22, 19, 2, 19, 1, 20, 5, 7, 3, 18, 22, 3, 22, 2, 4, 20, 18, 4, 18, 3, 5, 20, 4, 23, 12, 13, 24, 13, 14, 24, 14, 15, 17, 23, 13, 17, 13, 24, 0, 12, 23, 19, 12, 0, 0, 23, 17, 24, 15, 16, 17, 24, 16 ],
					"vertices": [ 2, 7, 43.46, 4.25, 0.92164, 8, -3.68, 4.25, 0.07836, 2, 7, 53.76, 7.48, 7.3E-4, 8, 6.63, 7.48, 0.99927, 1, 8, 16.93, 10.71, 1, 1, 8, 28.14, 13.51, 1, 1, 8, 39.35, 16.3, 1, 1, 8, 52.88, 12.53, 1, 1, 8, 60.82, 7.68, 1, 1, 8, 60.82, 4.15, 1, 1, 8, 60.82, 0.61, 1, 1, 8, 53.52, -4.54, 1, 1, 8, 46.22, -9.7, 1, 1, 8, 20.77, -7.67, 1, 2, 7, 44.47, -4.24, 0.87801, 8, -2.67, -4.24, 0.12199, 1, 7, 20.69, -4.37, 1, 1, 7, -1.05, -5.05, 1, 1, 7, -1.05, 0.38, 1, 1, 7, -1.05, 5.8, 1, 1, 7, 21.59, 3.54, 1, 1, 8, 35.23, 4.4, 1, 1, 8, 7.87, 0.75, 1, 1, 8, 47.47, 4.21, 1, 1, 8, 37.35, -2.22, 1, 1, 8, 23.63, 1.21, 1, 1, 7, 32.52, -0.22, 1, 1, 7, 7.88, 0.06, 1, 1, 8, 32.64, -2.81, 1 ],
					"hull": 18,
					"edges": [ 0, 2, 2, 4, 4, 6, 6, 8, 8, 10, 10, 12, 12, 14, 14, 16, 16, 18, 18, 20, 20, 22, 22, 24, 24, 26, 26, 28, 28, 30, 30, 32, 32, 34, 34, 0 ],
					"width": 109,
					"height": 26
				}
			}
		}
	}
],
"animations": {
	"Attack": {
		"slots": {
			"EffectSword": {
				"attachment": [
					{ "time": 0.0333, "name": "Attack1_1" },
					{ "time": 0.0667, "name": "Attack1_2" },
					{ "time": 0.1, "name": "Attack1_3" },
					{ "time": 0.1333, "name": "Attack1_4" },
					{ "time": 0.1667, "name": "Attack1_5" },
					{ "time": 0.2, "name": null }
				]
			}
		},
		"bones": {
			"HandL_2": {
				"rotate": [
					{ "angle": 117.88 },
					{ "time": 0.0333, "angle": 75.19 },
					{ "time": 0.0667, "angle": 48.85 },
					{ "time": 0.1, "angle": 34.84 }
				]
			},
			"HandL_1": {
				"rotate": [
					{ "angle": 168.33 },
					{ "time": 0.0333, "angle": 138.07 },
					{ "time": 0.0667, "angle": 126.27 },
					{ "time": 0.1, "angle": 64.85 }
				]
			},
			"HandR_2": {
				"rotate": [
					{ "angle": 132.39 },
					{ "time": 0.0333, "angle": 86.08 },
					{ "time": 0.0667, "angle": 53.49 },
					{ "time": 0.1, "angle": 75.76 }
				]
			},
			"HandR_1": {
				"rotate": [
					{ "angle": 58.03 },
					{ "time": 0.0333, "angle": -42.9 },
					{ "time": 0.0667, "angle": -53.57 },
					{ "time": 0.1, "angle": -152.6 }
				]
			},
			"sword": {
				"rotate": [
					{ "angle": -65.88 }
				],
				"translate": [
					{ "x": 21.42, "y": 18.11 }
				]
			},
			"Body": {
				"rotate": [
					{},
					{ "time": 0.0667, "angle": -5.25 },
					{ "time": 0.1, "angle": -7.64 }
				],
				"translate": [
					{ "x": -5.11, "y": -32.8 },
					{ "time": 0.0333, "x": -5.7, "y": -32.8 },
					{ "time": 0.0667, "x": 2.27, "y": -32.8 },
					{ "time": 0.1, "x": 10.93, "y": -46.8 }
				]
			},
			"LegL": {
				"translate": [
					{ "x": -55.26 }
				]
			},
			"LegR": {
				"translate": [
					{ "y": 0.72 }
				]
			}
		},
		"deform": {
			"Sword_2": {
				"MC": {
					"MC2": [
						{
							"offset": 24,
							"vertices": [ 0.8192, -0.73027, 0.7514, -0.79986, 0.76003, -0.79167, 0.77602, -0.776, -0.8978, 0.63113, -4.72849, -6.82029, -5.31404, -6.37527, -5.24492, -6.43248, -5.1128, -6.53814, 1.14587, 5.33471, -7.49492, 2.62094, -7.23569, 3.27355, -7.27147, 3.19485, -7.3357, 3.04601, 8.46893, 2.34762, -8.2356, -0.46111, -8.23038, -0.55033, -8.21764, -0.71812, 5.20449, 0.13468 ],
							"curve": "stepped"
						},
						{
							"time": 0.8333,
							"offset": 24,
							"vertices": [ 0.8192, -0.73027, 0.7514, -0.79986, 0.76003, -0.79167, 0.77602, -0.776, -0.8978, 0.63113, -4.72849, -6.82029, -5.31404, -6.37527, -5.24492, -6.43248, -5.1128, -6.53814, 1.14587, 5.33471, -7.49492, 2.62094, -7.23569, 3.27355, -7.27147, 3.19485, -7.3357, 3.04601, 8.46893, 2.34762, -8.2356, -0.46111, -8.23038, -0.55033, -8.21764, -0.71812, 5.20449, 0.13468 ]
						}
					]
				}
			}
		},
		"drawOrder": [
			{
				"offsets": [
					{ "slot": "Weapon_L", "offset": 4 }
				]
			}
		]
	},
	"Die": {
		"bones": {
			"HandL_2": {
				"rotate": [
					{ "angle": 12.67 },
					{ "time": 0.1667, "angle": 1.26, "curve": "stepped" },
					{ "time": 0.3333, "angle": 1.26 },
					{ "time": 0.6667, "angle": 57.05 },
					{ "time": 0.8333, "angle": 2.21 }
				]
			},
			"HandL_1": {
				"rotate": [
					{ "angle": 59.31 },
					{ "time": 0.1667, "angle": 46.23, "curve": "stepped" },
					{ "time": 0.3333, "angle": 46.23 },
					{ "time": 0.6667, "angle": 23.37 },
					{ "time": 0.8333, "angle": 100.88 }
				]
			},
			"HandR_2": {
				"rotate": [
					{ "angle": 6.36 },
					{ "time": 0.1667, "angle": 42.73 },
					{ "time": 0.5, "angle": 49.27 },
					{ "time": 0.8333, "angle": 15.31 }
				]
			},
			"HandR_1": {
				"rotate": [
					{ "angle": -70.96 },
					{ "time": 0.1667, "angle": -67.71 },
					{ "time": 0.5, "angle": -48.49 },
					{ "time": 0.8333, "angle": 54.79 }
				]
			},
			"sword": {
				"rotate": [
					{ "angle": -65.88 }
				]
			},
			"Body": {
				"rotate": [
					{},
					{ "time": 0.7333, "angle": -43.1 },
					{ "time": 0.8333, "angle": -88.01 }
				],
				"translate": [
					{},
					{ "time": 0.1, "y": -38.14 },
					{ "time": 0.1667, "x": 29.85, "y": -92.51, "curve": "stepped" },
					{ "time": 0.3333, "x": 29.85, "y": -92.51 },
					{ "time": 0.4, "x": 72.33, "y": -92.51 },
					{ "time": 0.7333, "x": 91.21, "y": -91.33 },
					{ "time": 0.8333, "x": 91.21, "y": -122.01 }
				]
			},
			"LegR": {
				"translate": [
					{},
					{ "time": 0.8333, "x": -57.82 }
				]
			},
			"LegL": {
				"translate": [
					{},
					{ "time": 0.8333, "x": 21.85, "y": 13.32 }
				]
			}
		}
	},
	"Idle": {
		"bones": {
			"HandL_2": {
				"rotate": [
					{ "angle": 12.67 },
					{ "time": 0.3333, "angle": 24.07 },
					{ "time": 1.1667, "angle": 12.67 }
				]
			},
			"HandL_1": {
				"rotate": [
					{ "angle": 59.31 },
					{ "time": 0.3333, "angle": 54.02 },
					{ "time": 1.1667, "angle": 59.31 }
				],
				"translate": [
					{ "x": -6.11, "y": 31.02 }
				]
			},
			"HandR_2": {
				"rotate": [
					{ "angle": 6.36 }
				]
			},
			"HandR_1": {
				"rotate": [
					{ "angle": -70.96 }
				]
			},
			"sword": {
				"rotate": [
					{ "angle": -65.88 }
				]
			},
			"Chest": {
				"translate": [
					{},
					{ "time": 0.3333, "x": 12.29, "y": 0.18 },
					{ "time": 1.1667 }
				]
			},
			"Head": {
				"rotate": [
					{},
					{ "time": 0.3333, "angle": 9.44 },
					{ "time": 1.1667 }
				]
			}
		}
	}
}
}