{"skeleton":{"hash":"OBdCK19Ev2CWQ4dhAF+NVSTukZw","spine":"3.8.75","x":-355,"y":-109.5,"width":720,"height":219,"images":"","audio":""},"bones":[{"name":"root"}],"slots":[{"name":"wq1","bone":"root","attachment":"wq1"},{"name":"wq2","bone":"root","attachment":"wq2"},{"name":"wq3","bone":"root","attachment":"wq3"},{"name":"wq4","bone":"root","attachment":"wq4"},{"name":"wq5","bone":"root","attachment":"wq5"},{"name":"wq6","bone":"root","attachment":"wq6"},{"name":"wq7","bone":"root","attachment":"wq7"},{"name":"wq8","bone":"root","attachment":"wq8"},{"name":"wq9","bone":"root","attachment":"wq9"},{"name":"ypwq1","bone":"root","attachment":"ypwq1"},{"name":"ypwq2","bone":"root","attachment":"ypwq2"},{"name":"ypwq3","bone":"root","attachment":"ypwq3"},{"name":"ypwq4","bone":"root","attachment":"ypwq4"},{"name":"ypwq5","bone":"root","attachment":"ypwq5"},{"name":"ypwq6","bone":"root","attachment":"ypwq6"},{"name":"ypwq7","bone":"root","attachment":"ypwq7"},{"name":"ypwq8","bone":"root","attachment":"ypwq8"}],"skins":[{"name":"default","attachments":{"wq1":{"wq1":{"width":710,"height":219}},"wq2":{"wq2":{"width":710,"height":219}},"wq3":{"wq3":{"width":710,"height":219}},"wq4":{"wq4":{"width":710,"height":219}},"wq5":{"wq5":{"width":710,"height":219}},"wq6":{"wq6":{"width":710,"height":219}},"wq7":{"wq7":{"width":710,"height":219}},"wq8":{"wq8":{"x":10,"width":710,"height":219}},"wq9":{"wq9":{"width":710,"height":219}},"ypwq1":{"ypwq1":{"width":710,"height":219}},"ypwq2":{"ypwq2":{"width":710,"height":219}},"ypwq3":{"ypwq3":{"width":710,"height":219}},"ypwq4":{"ypwq4":{"width":710,"height":219}},"ypwq5":{"ypwq5":{"width":710,"height":219}},"ypwq6":{"ypwq6":{"width":710,"height":219}},"ypwq7":{"ypwq7":{"width":710,"height":219}},"ypwq8":{"ypwq8":{"width":710,"height":219}}}}],"animations":{"animation":{}}}